tests/__init__.py
tests/python/__init__.py
tests/python/test_examples.py
tests/python/test_dynamic_bin_val.py
tests/python/test_experiment.py
tests/python/test_logger.py
tests/python/test_downloader.py
tests/python/test_package.py
tests/python/test_array_layout.py
tests/python/test_problem.py
tests/python/test_wrap_problem.py
ioh/__init__.py
ioh/iohcpp.cpython-311-x86_64-linux-gnu.so
ioh/__init__.pyi
ioh/static/dynamic_bin_val.in
ioh/static/example_list_maxinfluence
ioh/static/bbobfitness20.in
ioh/static/cec_problem2022.in
ioh/static/example_list_pwt
ioh/static/conf.ini
ioh/static/example_list_maxcut
ioh/static/pbofitness16.in
ioh/static/bbobfitness5.in
ioh/static/example_list_maxcoverage
ioh/static/cec_problem2013.in
ioh/static/pbofitness100.in
ioh/static/example_pwt/pla33810_n338090_uncorr_10.ttp
ioh/static/example_pwt/pla33810_n169045_uncorr-similar-weights_05.ttp
ioh/static/example_pwt/fnl4461_n4460_bounded-strongly-corr_01.ttp
ioh/static/example_pwt/a280_n279_bounded-strongly-corr_01.ttp
ioh/static/example_pwt/fnl4461_n44600_uncorr_10.ttp
ioh/static/example_pwt/pla33810_n33809_bounded-strongly-corr_01.ttp
ioh/static/example_pwt/a280_n2790_uncorr_10.ttp
ioh/static/example_pwt/fnl4461_n22300_uncorr-similar-weights_05.ttp
ioh/static/example_pwt/a280_n1395_uncorr-similar-weights_05.ttp
ioh/static/example_graphs/facebook_combined_e
ioh/static/example_graphs/example_graph1
ioh/static/example_graphs/example_graph0_c_linear
ioh/static/example_graphs/example_graph2_c_linear
ioh/static/example_graphs/example_graph3_c_linear
ioh/static/example_graphs/example_graph1_c_unweighted
ioh/static/example_graphs/email-Eu-core
ioh/static/example_graphs/example_graph2_c_unweighted
ioh/static/example_graphs/example_graph1_c_quadratic
ioh/static/example_graphs/facebook_combined_c_unweighted_3
ioh/static/example_graphs/G1
ioh/static/example_graphs/facebook_combined_c_linear_4
ioh/static/example_graphs/G4
ioh-0.3.22.dist-info/RECORD
ioh-0.3.22.dist-info/WHEEL
ioh-0.3.22.dist-info/top_level.txt
ioh-0.3.22.dist-info/METADATA
ioh-0.3.22.dist-info/licenses/LICENSE.md
