Metadata-Version: 2.4
Name: ioh
Version: 0.3.22
Summary: The experimenter for Iterative Optimization Heuristics
Home-page: https://iohprofiler.github.io/IOHexperimenter
Author: Jacob de Nobel, Furong Ye, Diederick Vermetten, Hao Wang, Carola Doerr and Thomas Bäck
Author-email: iohprofiler@liacs.leidenuniv.nl
License: BSD
Requires-Python: >=3.9
License-File: LICENSE.md
Requires-Dist: numpy>=2.0
Dynamic: author
Dynamic: author-email
Dynamic: description
Dynamic: description-content-type
Dynamic: home-page
Dynamic: license
Dynamic: license-file
Dynamic: requires-dist
Dynamic: requires-python
Dynamic: summary
